<xml xmlns="http://www.w3.org/1999/xhtml">
  <block type="arduino_functions" id=",(7kIe|_opGrFEbsECBc" x="367" y="47">
    <statement name="LOOP_FUNC">
      <block type="procedures_callnoreturn" id="i(8:6[7Ybv_h{S!PLN;O">
        <mutation name="ir output"></mutation>
      </block>
    </statement>
  </block>
  <block type="procedures_defnoreturn" id="=n[ayddoI%iV2~wtjtC;" x="580" y="151">
    <field name="NAME">ir output</field>
    <comment pinned="false" h="80" w="160">Describe this function...</comment>
    <statement name="STACK">
      <block type="controls_if" id="l}n?++aB]lZcAF[v!wl?">
        <mutation else="1"></mutation>
        <value name="IF0">
          <block type="io_digitalread" id="iiC*=,.Sw[`KD@DM|n@]">
            <field name="PIN">5</field>
          </block>
        </value>
        <statement name="DO0">
          <block type="procedures_callnoreturn" id="}9:H6*oxngpql},*QP^]">
            <mutation name="off"></mutation>
          </block>
        </statement>
        <statement name="ELSE">
          <block type="procedures_callnoreturn" id="KejpRhT|ByG~;TR*D05S">
            <mutation name="go forware"></mutation>
          </block>
        </statement>
      </block>
    </statement>
  </block>
  <block type="procedures_defnoreturn" id="+9B9:0zGy#:5(YzzSvYQ" x="399" y="363">
    <field name="NAME">off</field>
    <comment pinned="false" h="80" w="160">Describe this function...</comment>
    <statement name="STACK">
      <block type="io_digitalwrite" id="sccfC%7nQv!pC!w:JMd#">
        <field name="PIN">6</field>
        <value name="STATE">
          <block type="io_highlow" id=")#,?B9q./2.CzAyc#w_k">
            <field name="STATE">LOW</field>
          </block>
        </value>
        <next>
          <block type="io_digitalwrite" id="Oh0+?#sjR@|l~R0,6OSI">
            <field name="PIN">7</field>
            <value name="STATE">
              <block type="io_highlow" id="AQ%#0X/t=b}cE6+2loHL">
                <field name="STATE">LOW</field>
              </block>
            </value>
            <next>
              <block type="io_digitalwrite" id="gL?Q90?i?HD:;CU.j]2e">
                <field name="PIN">8</field>
                <value name="STATE">
                  <block type="io_highlow" id="[5*ZG;cqxmpimvcykc[p">
                    <field name="STATE">LOW</field>
                  </block>
                </value>
                <next>
                  <block type="io_digitalwrite" id="c@9]j3y@8:pCy9RXo~ft">
                    <field name="PIN">9</field>
                    <value name="STATE">
                      <block type="io_highlow" id="|Nkf*wm[KL=@}.]N6_x[">
                        <field name="STATE">LOW</field>
                      </block>
                    </value>
                  </block>
                </next>
              </block>
            </next>
          </block>
        </next>
      </block>
    </statement>
  </block>
  <block type="procedures_defnoreturn" id="!*A1ECcP3*%9bx+}N(GR" x="392" y="521">
    <field name="NAME">go forware</field>
    <comment pinned="false" h="80" w="160">Describe this function...</comment>
    <statement name="STACK">
      <block type="io_digitalwrite" id="}(F8nsTcxx[PZPBKctU4">
        <field name="PIN">6</field>
        <value name="STATE">
          <block type="io_highlow" id="Y^2G9r[uJz9`e`oxGAJm">
            <field name="STATE">HIGH</field>
          </block>
        </value>
        <next>
          <block type="io_digitalwrite" id="B7-^m9.xSi|@EQrwP`aw">
            <field name="PIN">7</field>
            <value name="STATE">
              <block type="io_highlow" id="ZT6`2,Y+M.TDma?P-@+c">
                <field name="STATE">LOW</field>
              </block>
            </value>
            <next>
              <block type="io_digitalwrite" id="D3A~p1rZR3R^7q!@#87P">
                <field name="PIN">8</field>
                <value name="STATE">
                  <block type="io_highlow" id="Xkn7JN3c+#Hcj?iaNvTP">
                    <field name="STATE">HIGH</field>
                  </block>
                </value>
                <next>
                  <block type="io_digitalwrite" id="UR#QUWEl*hk?c#8OV.PF">
                    <field name="PIN">9</field>
                    <value name="STATE">
                      <block type="io_highlow" id="p#-W}xX}oFonQP9:9g%p">
                        <field name="STATE">LOW</field>
                      </block>
                    </value>
                  </block>
                </next>
              </block>
            </next>
          </block>
        </next>
      </block>
    </statement>
  </block>
</xml>